awnf/__init__.py
awnf/adaptive_weighted_snf.py
awnf-0.1.3.dist-info/licenses/LICENSE.txt
awnf-0.1.3.dist-info/METADATA
awnf-0.1.3.dist-info/WHEEL
awnf-0.1.3.dist-info/top_level.txt
awnf-0.1.3.dist-info/RECORD
