Metadata-Version: 2.4
Name: awnf
Version: 0.1.3
Summary: A package for adaptive weighted similarity network fusion
Author: Sevinj Yolchuyeva
Author-email: sevinj.yolchuyeva@crchudequebec.ulaval.ca
Classifier: Programming Language :: Python :: 3
Classifier: License :: OSI Approved :: MIT License
Classifier: Operating System :: OS Independent
Requires-Python: >=3.6
License-File: LICENSE.txt
Requires-Dist: numpy
Requires-Dist: scipy
Requires-Dist: scikit-learn
Requires-Dist: boruta
Requires-Dist: snfpy
Dynamic: author
Dynamic: author-email
Dynamic: classifier
Dynamic: description
Dynamic: description-content-type
Dynamic: license-file
Dynamic: requires-dist
Dynamic: requires-python
Dynamic: summary
